flask_template_refs/__init__.py
flask_template_refs/errors.py
flask_template_refs/ftr.py
flask_template_refs/references.py
flask_template_refs/references.pyi
flask_template_refs-0.2.0.dist-info/METADATA
flask_template_refs-0.2.0.dist-info/WHEEL
flask_template_refs-0.2.0.dist-info/RECORD
